kopf/__init__.py
kopf/__main__.py
kopf/cli.py
kopf/on.py
kopf/py.typed
kopf/testing.py
kopf/_cogs/__init__.py
kopf/_cogs/aiokits/__init__.py
kopf/_cogs/aiokits/aioadapters.py
kopf/_cogs/aiokits/aiobindings.py
kopf/_cogs/aiokits/aioenums.py
kopf/_cogs/aiokits/aiotasks.py
kopf/_cogs/aiokits/aiotime.py
kopf/_cogs/aiokits/aiotoggles.py
kopf/_cogs/aiokits/aiovalues.py
kopf/_cogs/clients/__init__.py
kopf/_cogs/clients/api.py
kopf/_cogs/clients/auth.py
kopf/_cogs/clients/creating.py
kopf/_cogs/clients/errors.py
kopf/_cogs/clients/events.py
kopf/_cogs/clients/fetching.py
kopf/_cogs/clients/patching.py
kopf/_cogs/clients/scanning.py
kopf/_cogs/clients/watching.py
kopf/_cogs/configs/__init__.py
kopf/_cogs/configs/configuration.py
kopf/_cogs/configs/conventions.py
kopf/_cogs/configs/diffbase.py
kopf/_cogs/configs/progress.py
kopf/_cogs/helpers/.gitignore
kopf/_cogs/helpers/__init__.py
kopf/_cogs/helpers/hostnames.py
kopf/_cogs/helpers/loaders.py
kopf/_cogs/helpers/thirdparty.py
kopf/_cogs/helpers/typedefs.py
kopf/_cogs/helpers/versions.py
kopf/_cogs/structs/__init__.py
kopf/_cogs/structs/bodies.py
kopf/_cogs/structs/credentials.py
kopf/_cogs/structs/dicts.py
kopf/_cogs/structs/diffs.py
kopf/_cogs/structs/ephemera.py
kopf/_cogs/structs/finalizers.py
kopf/_cogs/structs/ids.py
kopf/_cogs/structs/patches.py
kopf/_cogs/structs/references.py
kopf/_cogs/structs/reviews.py
kopf/_core/__init__.py
kopf/_core/actions/__init__.py
kopf/_core/actions/application.py
kopf/_core/actions/execution.py
kopf/_core/actions/invocation.py
kopf/_core/actions/lifecycles.py
kopf/_core/actions/loggers.py
kopf/_core/actions/progression.py
kopf/_core/actions/throttlers.py
kopf/_core/engines/__init__.py
kopf/_core/engines/activities.py
kopf/_core/engines/admission.py
kopf/_core/engines/daemons.py
kopf/_core/engines/indexing.py
kopf/_core/engines/peering.py
kopf/_core/engines/posting.py
kopf/_core/engines/probing.py
kopf/_core/intents/__init__.py
kopf/_core/intents/callbacks.py
kopf/_core/intents/causes.py
kopf-1.42.2.dist-info/licenses/LICENSE
kopf-1.42.2.dist-info/METADATA
kopf-1.42.2.dist-info/WHEEL
kopf-1.42.2.dist-info/entry_points.txt
kopf-1.42.2.dist-info/top_level.txt
kopf-1.42.2.dist-info/RECORD
