Metadata-Version: 2.4
Name: kopf
Version: 1.42.2
Summary: Kubernetes Operator Pythonic Framework (Kopf)
Author-email: Sergey Vasilyev <nolar@nolar.info>
Maintainer-email: Sergey Vasilyev <nolar@nolar.info>
License-Expression: MIT
Project-URL: homepage, https://github.com/nolar/kopf
Project-URL: repository, https://github.com/nolar/kopf
Project-URL: documentation, https://kopf.readthedocs.io
Keywords: kubernetes,operator,framework,python,k8s
Classifier: Intended Audience :: Developers
Classifier: Operating System :: OS Independent
Classifier: Programming Language :: Python
Classifier: Programming Language :: Python :: 3
Classifier: Programming Language :: Python :: 3.10
Classifier: Programming Language :: Python :: 3.11
Classifier: Programming Language :: Python :: 3.12
Classifier: Programming Language :: Python :: 3.13
Classifier: Programming Language :: Python :: 3.14
Classifier: Programming Language :: Python :: 3 :: Only
Classifier: Programming Language :: Python :: Implementation :: CPython
Classifier: Programming Language :: Python :: Implementation :: PyPy
Classifier: Topic :: Software Development :: Libraries
Requires-Python: >=3.10
License-File: LICENSE
Requires-Dist: python-json-logger
Requires-Dist: iso8601
Requires-Dist: pyyaml
Requires-Dist: click>=8.2.0
Requires-Dist: aiohttp
Requires-Dist: aiohttp>=3.9.0; python_version >= "3.12"
Provides-Extra: full-auth
Requires-Dist: pykube-ng; extra == "full-auth"
Requires-Dist: kubernetes; extra == "full-auth"
Provides-Extra: uvloop
Requires-Dist: uvloop; extra == "uvloop"
Requires-Dist: uvloop>=0.18.0; python_version >= "3.12" and extra == "uvloop"
Provides-Extra: dev
Requires-Dist: oscrypto; extra == "dev"
Requires-Dist: certbuilder; extra == "dev"
Requires-Dist: certvalidator; extra == "dev"
Requires-Dist: pyngrok; extra == "dev"
Dynamic: license-file
